conjure/__init__.py
conjure/conjure_client.py
conjure/models/__init__.py
conjure/models/annotation/__init__.py
conjure/models/annotation/bounding_box.py
conjure/models/annotation/classification.py
conjure/models/annotation/object_detection.py
python_conjure-0.1.0.dist-info/LICENSE
python_conjure-0.1.0.dist-info/METADATA
python_conjure-0.1.0.dist-info/WHEEL
python_conjure-0.1.0.dist-info/top_level.txt
python_conjure-0.1.0.dist-info/RECORD
