Metadata-Version: 2.1
Name: python-conjure
Version: 0.1.0
Summary: Conjure AI's Python SDK
Author-email: Conjure AI <kyle@conjure-ai.com>
License: MIT
Requires-Python: >=3.11
License-File: LICENSE
Requires-Dist: pydantic >=2.6.0
Requires-Dist: httpx >=0.26.0
